src/__init__.py
src/cli/analyze_issues.py
src/cli/commands/__init__.py
src/cli/commands/check.py
src/cli/commands/docs.py
src/cli/commands/init.py
src/cli/commands/types.py
src/cli/commands/yaml.py
src/cli/main.py
src/cli/utils.py
src/core/analyzer/__init__.py
src/core/analyzer/abc_base.py
src/core/analyzer/ast_visitors.py
src/core/analyzer/base.py
src/core/analyzer/code_locator.py
src/core/analyzer/dependency_extractor.py
src/core/analyzer/docstring_analyzer.py
src/core/analyzer/exceptions.py
src/core/analyzer/factory_usage_checker.py
src/core/analyzer/graph_processor.py
src/core/analyzer/improvement_templates.py
src/core/analyzer/models.py
src/core/analyzer/protocols.py
src/core/analyzer/quality_checker.py
src/core/analyzer/quality_models.py
src/core/analyzer/quality_reporter.py
src/core/analyzer/schema.lay.yaml
src/core/analyzer/strategies.py
src/core/analyzer/type_classifier.py
src/core/analyzer/type_ignore_analyzer.py
src/core/analyzer/type_ignore_reporter.py
src/core/analyzer/type_inferrer.py
src/core/analyzer/type_level_analyzer.py
src/core/analyzer/type_level_models.py
src/core/analyzer/type_reporter.py
src/core/analyzer/type_statistics.py
src/core/analyzer/type_upgrade_analyzer.py
src/core/analyzer/types.py
src/core/converters/__init__.py
src/core/converters/ast_dependency_extractor.py
src/core/converters/clean_regeneration.py
src/core/converters/extract_deps.py
src/core/converters/generation_header.py
src/core/converters/models.py
src/core/converters/mypy_type_extractor.py
src/core/converters/path_mirror.py
src/core/converters/protocols.py
src/core/converters/type_to_yaml.py
src/core/converters/type_to_yaml.py.deps.yaml
src/core/converters/types.py
src/core/converters/yaml_to_type.py
src/core/doc_generators/README.md
src/core/doc_generators/__init__.py
src/core/doc_generators/base.py
src/core/doc_generators/config.py
src/core/doc_generators/filesystem.py
src/core/doc_generators/graph_doc_generator.py
src/core/doc_generators/markdown_builder.py
pylay-0.5.1.dist-info/METADATA
pylay-0.5.1.dist-info/WHEEL
pylay-0.5.1.dist-info/entry_points.txt
pylay-0.5.1.dist-info/licenses/LICENSE
pylay-0.5.1.dist-info/RECORD
