Metadata-Version: 2.4
Name: pylay
Version: 0.5.1
Summary: Python の type hint と docstrings を利用した types <-> docs 間の透過的なジェネレータ
License: MIT License
License-File: LICENSE
Keywords: python,type-hints,pydantic,yaml,documentation,generator
Author: Ryo HIGASIGAWA
Author-email: your.email@example.com
Requires-Python: >=3.12
Classifier: Programming Language :: Python :: 3
Classifier: Programming Language :: Python :: 3.12
Classifier: Programming Language :: Python :: 3.13
Classifier: License :: OSI Approved :: MIT License
Classifier: Operating System :: OS Independent
Classifier: Development Status :: 4 - Beta
Classifier: Topic :: Software Development :: Documentation
Classifier: Topic :: Software Development :: Code Generators
Provides-Extra: dev
Provides-Extra: viz
Requires-Dist: click (>=8.3.0)
Requires-Dist: interrogate (>=1.7.0) ; extra == "dev"
Requires-Dist: matplotlib (>=3.10.6)
Requires-Dist: matplotlib (>=3.5.0) ; extra == "viz"
Requires-Dist: mypy (>=1.18.2)
Requires-Dist: mypy (>=1.18.2) ; extra == "dev"
Requires-Dist: networkx (>=3.3)
Requires-Dist: networkx (>=3.3) ; extra == "dev"
Requires-Dist: networkx (>=3.3) ; extra == "viz"
Requires-Dist: pre-commit (>=3.0.0) ; extra == "dev"
Requires-Dist: pydantic (>=2.8.2)
Requires-Dist: pydot (>=3.0.0) ; extra == "dev"
Requires-Dist: pytest (>=8.3.3) ; extra == "dev"
Requires-Dist: pytest-cov (>=4.0.0) ; extra == "dev"
Requires-Dist: pytest-xdist (>=3.0.0) ; extra == "dev"
Requires-Dist: pyyaml (>=6.0.2)
Requires-Dist: radon (>=6.0.1) ; extra == "dev"
Requires-Dist: rich (>=13.7.0)
Requires-Dist: ruamel-yaml (>=0.18.6)
Requires-Dist: ruff (>=0.6.0) ; extra == "dev"
Requires-Dist: safety (>=3.2.3) ; extra == "dev"
Project-URL: Homepage, https://github.com/biwakonbu/pylay
Project-URL: Repository, https://github.com/biwakonbu/pylay.git
